confighandler/__init__.py
python_confighandler-0.2.1.dist-info/LICENSE
python_confighandler-0.2.1.dist-info/METADATA
python_confighandler-0.2.1.dist-info/WHEEL
python_confighandler-0.2.1.dist-info/top_level.txt
python_confighandler-0.2.1.dist-info/RECORD
