Metadata-Version: 2.1
Name: python-confighandler
Version: 0.2.1
Summary: Python Confighandler
Home-page: https://github.com/FourZeroOne/python_confighandler
Author: Johannes Eimer Production (JEP)
Author-email: info@jep-dev.com
License: MIT
